odoo/addons/base_import_odoo/README.rst
odoo/addons/base_import_odoo/__init__.py
odoo/addons/base_import_odoo/__manifest__.py
odoo/addons/base_import_odoo/demo/import_odoo_database.xml
odoo/addons/base_import_odoo/demo/import_odoo_database_field.xml
odoo/addons/base_import_odoo/demo/import_odoo_database_model.xml
odoo/addons/base_import_odoo/demo/ir_attachment.xml
odoo/addons/base_import_odoo/demo/res_partner.xml
odoo/addons/base_import_odoo/demo/res_users.xml
odoo/addons/base_import_odoo/i18n/am.po
odoo/addons/base_import_odoo/i18n/ar.po
odoo/addons/base_import_odoo/i18n/base_import_odoo.pot
odoo/addons/base_import_odoo/i18n/bg.po
odoo/addons/base_import_odoo/i18n/bs.po
odoo/addons/base_import_odoo/i18n/ca.po
odoo/addons/base_import_odoo/i18n/ca_ES.po
odoo/addons/base_import_odoo/i18n/cs.po
odoo/addons/base_import_odoo/i18n/da.po
odoo/addons/base_import_odoo/i18n/da_DK.po
odoo/addons/base_import_odoo/i18n/de.po
odoo/addons/base_import_odoo/i18n/el_GR.po
odoo/addons/base_import_odoo/i18n/en_GB.po
odoo/addons/base_import_odoo/i18n/es.po
odoo/addons/base_import_odoo/i18n/es_AR.po
odoo/addons/base_import_odoo/i18n/es_CL.po
odoo/addons/base_import_odoo/i18n/es_CO.po
odoo/addons/base_import_odoo/i18n/es_CR.po
odoo/addons/base_import_odoo/i18n/es_DO.po
odoo/addons/base_import_odoo/i18n/es_EC.po
odoo/addons/base_import_odoo/i18n/es_ES.po
odoo/addons/base_import_odoo/i18n/es_MX.po
odoo/addons/base_import_odoo/i18n/es_PE.po
odoo/addons/base_import_odoo/i18n/es_PY.po
odoo/addons/base_import_odoo/i18n/es_VE.po
odoo/addons/base_import_odoo/i18n/et.po
odoo/addons/base_import_odoo/i18n/eu.po
odoo/addons/base_import_odoo/i18n/fa.po
odoo/addons/base_import_odoo/i18n/fi.po
odoo/addons/base_import_odoo/i18n/fr.po
odoo/addons/base_import_odoo/i18n/fr_CA.po
odoo/addons/base_import_odoo/i18n/fr_CH.po
odoo/addons/base_import_odoo/i18n/fr_FR.po
odoo/addons/base_import_odoo/i18n/gl.po
odoo/addons/base_import_odoo/i18n/gl_ES.po
odoo/addons/base_import_odoo/i18n/he.po
odoo_addon_base_import_odoo-16.0.1.0.0.11.dist-info/METADATA
odoo_addon_base_import_odoo-16.0.1.0.0.11.dist-info/WHEEL
odoo_addon_base_import_odoo-16.0.1.0.0.11.dist-info/top_level.txt
odoo_addon_base_import_odoo-16.0.1.0.0.11.dist-info/RECORD
